iqmma/__init__.py
iqmma/cli.py
iqmma/default.ini
iqmma/iqmma.py
iqmma/utils.py
iqmma-0.1.6.4.dist-info/LICENSE
iqmma-0.1.6.4.dist-info/METADATA
iqmma-0.1.6.4.dist-info/WHEEL
iqmma-0.1.6.4.dist-info/entry_points.txt
iqmma-0.1.6.4.dist-info/top_level.txt
iqmma-0.1.6.4.dist-info/RECORD
